autostar/__init__.py
autostar/bad_stars.py
autostar/exo_archive.py
autostar/import_stars.py
autostar/name_correction.py
autostar/object_params.py
autostar/read_gaia.py
autostar/simbad_names.py
autostar/simbad_query.py
autostar/table_read.py
autostar/tic_query.py
autostar/wise.py
autostar/config/__init__.py
autostar/config/datapaths.py
autostar/config/default.toml
autostar/config/default_star_names.py
autostar/config/name_correction.psv
autostar-0.1.4.data/data/autostar/config/default.toml
autostar-0.1.4.dist-info/LICENSE.md
autostar-0.1.4.dist-info/METADATA
autostar-0.1.4.dist-info/WHEEL
autostar-0.1.4.dist-info/top_level.txt
autostar-0.1.4.dist-info/RECORD
